supGeckoASM/__init__.py
supGeckoASM/cli.py
supGeckoASM/include/macros.inc
supGeckoASM/ldscript/NTSC-J_1.0.ld
supGeckoASM/ldscript/NTSC-J_1.1.ld
supGeckoASM/ldscript/common.ld
supGeckoASM-0.0.1a4.dist-info/LICENSE
supGeckoASM-0.0.1a4.dist-info/METADATA
supGeckoASM-0.0.1a4.dist-info/WHEEL
supGeckoASM-0.0.1a4.dist-info/entry_points.txt
supGeckoASM-0.0.1a4.dist-info/top_level.txt
supGeckoASM-0.0.1a4.dist-info/RECORD
